logregnumpy/LogRegNumpy.py
logregnumpy/__init__.py
logregnumpy-0.1.2.dist-info/METADATA
logregnumpy-0.1.2.dist-info/WHEEL
logregnumpy-0.1.2.dist-info/top_level.txt
logregnumpy-0.1.2.dist-info/RECORD
