Metadata-Version: 2.1
Name: logregnumpy
Version: 0.1.2
Summary: Logistic Regression Classifier
Home-page: UNKNOWN
Author-email: kir.klyukvin@gmail.com
License: UNKNOWN
Platform: UNKNOWN
